README.md
setup.py
src/mybuilder/__init__.py
src/mybuilder/mydb.py
src/mybuilder/mytest.py
src/mybuilder.egg-info/PKG-INFO
src/mybuilder.egg-info/SOURCES.txt
src/mybuilder.egg-info/dependency_links.txt
src/mybuilder.egg-info/top_level.txt