Metadata-Version: 1.1
Name: mybuilder
Version: 0.0.1
Summary: 上海弥云科技-数据分析模块
Home-page: https://github.com/miitec/mybuilder
Author: xinghui.wu
Author-email: xinghui.wu@mii-tec.com
License: UNKNOWN
Platform: UNKNOWN
Classifier: Intended Audience :: Developers
Classifier: Operating System :: OS Independent
Classifier: Natural Language :: Chinese (Simplified)
Classifier: Programming Language :: Python
Classifier: Programming Language :: Python :: 2.7
Classifier: Programming Language :: Python :: 3.4
Classifier: Programming Language :: Python :: 3.6
Classifier: Programming Language :: Python :: 3.7
Classifier: Programming Language :: Python :: 3.8
Classifier: Topic :: Utilities
